ekphrasis/__init__.py
ekphrasis/classes/__init__.py
ekphrasis/classes/exmanager.py
ekphrasis/classes/preprocessor.py
ekphrasis/classes/segmenter.py
ekphrasis/classes/spellcorrect.py
ekphrasis/classes/tokenizer.py
ekphrasis/dicts/__init__.py
ekphrasis/dicts/emoticons.py
ekphrasis/dicts/noslang/__init__.py
ekphrasis/dicts/noslang/manager.py
ekphrasis/dicts/noslang/slangdict.py
ekphrasis/dicts/sentiment/__init__.py
ekphrasis/dicts/sentiment/nrc_emolex/NRCEmolex.py
ekphrasis/dicts/sentiment/nrc_emolex/__init__.py
ekphrasis/examples/__init__.py
ekphrasis/examples/demo_data.py
ekphrasis/examples/demo_ext.py
ekphrasis/examples/demo_segmenter.py
ekphrasis/examples/demo_tok.py
ekphrasis/examples/example.py
ekphrasis/examples/sentiment.py
ekphrasis/regexes/__init__.py
ekphrasis/regexes/expressions.txt
ekphrasis/regexes/generate_expressions.py
ekphrasis/tools/__init__.py
ekphrasis/tools/generate_stats.py
ekphrasis/utils/__init__.py
ekphrasis/utils/helpers.py
ekphrasis/utils/nlp.py
ekphrasis-0.5.4.dist-info/LICENCE
ekphrasis-0.5.4.dist-info/METADATA
ekphrasis-0.5.4.dist-info/WHEEL
ekphrasis-0.5.4.dist-info/top_level.txt
ekphrasis-0.5.4.dist-info/RECORD
