Metadata-Version: 1.0
Name: ekphrasis
Version: 0.5.4
Summary: Text processing tool, geared towards text from social networks, such as Twitter or Facebook. Ekphrasis performs tokenization, word normalization, word segmentation (for splitting hashtags) and spell correction.
Home-page: https://github.com/cbaziotis/ekphrasis
Author: Christos Baziotis
Author-email: christos.baziotis@gmail.com
License: MIT
Platform: UNKNOWN
